configpilot/__init__.py
configpilot/exceptions.py
configpilot/models.py
configpilot/parsers.py
configpilot/pilot.py
configpilot/utils.py
configpilot-1.1.dist-info/LICENSE
configpilot-1.1.dist-info/METADATA
configpilot-1.1.dist-info/WHEEL
configpilot-1.1.dist-info/top_level.txt
configpilot-1.1.dist-info/RECORD
