Metadata-Version: 2.1
Name: configpilot
Version: 1.1
Summary: A lightweight and powerful configuration parser for Python that automates checks and typecasting.
Home-page: https://github.com/ValentinBELYN/configpilot
Author: Valentin BELYN
Author-email: valentin-hello@gmx.com
License: MIT License
Keywords: lightweight,configuration,parser,ini,python3
Platform: UNKNOWN
Classifier: Development Status :: 5 - Production/Stable
Classifier: Intended Audience :: Developers
Classifier: License :: OSI Approved :: MIT License
Classifier: Operating System :: OS Independent
Classifier: Programming Language :: Python :: 3
Classifier: Programming Language :: Python :: 3 :: Only
Classifier: Programming Language :: Python :: 3.6
Classifier: Programming Language :: Python :: 3.7
Classifier: Programming Language :: Python :: 3.8
Classifier: Topic :: Software Development :: Libraries
Classifier: Topic :: Software Development :: Libraries :: Python Modules
Requires-Python: >=3.6
